docdog/__init__.py
docdog/chunking.py
docdog/find_proj_root.py
docdog/main.py
docdog/p1_analysis_helper.py
docdog/p2_readme_generator.py
docdog/p3_validate_readme.py
docdog/p4_save_readme.py
docdog/readme_template.md
docdog/tools.py
docdog-0.0.4.dist-info/licenses/LICENSE
docdog-0.0.4.dist-info/METADATA
docdog-0.0.4.dist-info/WHEEL
docdog-0.0.4.dist-info/entry_points.txt
docdog-0.0.4.dist-info/top_level.txt
docdog-0.0.4.dist-info/RECORD
