Metadata-Version: 2.4
Name: docdog
Version: 0.0.4
Summary: A tool for summarizing documents and code using AI
Author-email: oha <aaronoh2015@gmail.com>
License: Apache-2.0
Classifier: Programming Language :: Python :: 3
Classifier: License :: OSI Approved :: Apache Software License
Classifier: Operating System :: OS Independent
Requires-Python: >=3.8
License-File: LICENSE
Requires-Dist: python-dotenv>=0.19.0
Requires-Dist: pykomodo>=0.1.5
Requires-Dist: jinja2
Requires-Dist: colorama>=0.4.6
Requires-Dist: anthropic>=0.49.0
Dynamic: license-file
